saucelab_api_client/__init__.py
saucelab_api_client/category.py
saucelab_api_client/saucelab_api_client.py
saucelab_api_client/session.py
saucelab_api_client/base_classes/__init__.py
saucelab_api_client/base_classes/accounts_api.py
saucelab_api_client/base_classes/exceptions.py
saucelab_api_client/base_classes/insights_api.py
saucelab_api_client/base_classes/insights_real_devices_api.py
saucelab_api_client/base_classes/job_api.py
saucelab_api_client/base_classes/performance_api.py
saucelab_api_client/base_classes/platform_api.py
saucelab_api_client/base_classes/real_devices_api.py
saucelab_api_client/base_classes/sauce_connect_api.py
saucelab_api_client/base_classes/storage_api.py
saucelab_api_client/models/__init__.py
saucelab_api_client/models/accounts.py
saucelab_api_client/models/build.py
saucelab_api_client/models/device.py
saucelab_api_client/models/file.py
saucelab_api_client/models/group.py
saucelab_api_client/models/insights.py
saucelab_api_client/models/job.py
saucelab_api_client/models/performance.py
saucelab_api_client/models/platform_.py
saucelab_api_client/models/real_device_job.py
saucelab_api_client/models/sauce_connect.py
saucelab_api_client/models/service.py
saucelab_api_client-0.6.2.dist-info/LICENSE
saucelab_api_client-0.6.2.dist-info/METADATA
saucelab_api_client-0.6.2.dist-info/WHEEL
saucelab_api_client-0.6.2.dist-info/entry_points.txt
saucelab_api_client-0.6.2.dist-info/top_level.txt
saucelab_api_client-0.6.2.dist-info/RECORD
