Metadata-Version: 2.1
Name: saucelab-api-client
Version: 0.6.2
Summary: SauceLab Api Python Client
Home-page: https://github.com/Slamnlc/saucelab-api-client
Author: Biriukov Maksym
Author-email: maximbirukov77@gmail.com
License: UNKNOWN
Download-URL: https://github.com/Slamnlc/saucelab-api-client/archive/refs/tags/v0.6.2.tar.gz
Platform: UNKNOWN
License-File: LICENSE
Requires-Dist: requests
